santodigital_gcpLogging/__init__.py
santodigital_gcpLogging-0.0.4.dist-info/LICENSE
santodigital_gcpLogging-0.0.4.dist-info/METADATA
santodigital_gcpLogging-0.0.4.dist-info/WHEEL
santodigital_gcpLogging-0.0.4.dist-info/top_level.txt
santodigital_gcpLogging-0.0.4.dist-info/RECORD
