Metadata-Version: 2.1
Name: santodigital-gcpLogging
Version: 0.0.4
Summary: A package to register GCP loggings
Home-page: UNKNOWN
Author: Mohamed Rasvi
Author-email: developer@santodigital.com.br
License: UNKNOWN
Platform: UNKNOWN
Classifier: Programming Language :: Python :: 3
Classifier: License :: OSI Approved :: MIT License
Classifier: Operating System :: OS Independent
Requires-Python: >=3.6
